setup_py_demo/__init__.py
setup_py_demo/main.py
setup_py_demo-0.6.dist-info/METADATA
setup_py_demo-0.6.dist-info/WHEEL
setup_py_demo-0.6.dist-info/entry_points.txt
setup_py_demo-0.6.dist-info/top_level.txt
setup_py_demo-0.6.dist-info/RECORD
