Metadata-Version: 2.1
Name: setup_py_demo
Version: 0.6
Summary: UNKNOWN
Home-page: UNKNOWN
License: UNKNOWN
Platform: UNKNOWN
